zjucrawler/__init__.py
zjucrawler/chalaoshi_fetcher.py
zjucrawler/school_crawler.py
zjucrawler/security.js
zjucrawler-1.0.1.dist-info/LICENSE
zjucrawler-1.0.1.dist-info/METADATA
zjucrawler-1.0.1.dist-info/WHEEL
zjucrawler-1.0.1.dist-info/top_level.txt
zjucrawler-1.0.1.dist-info/RECORD
