Metadata-Version: 2.1
Name: zjucrawler
Version: 1.0.1
Home-page: https://github.com/cubicYYY/ZJUCrawler
Author: cubicYYY
License: MIT
Classifier: Development Status :: 3 - Alpha
Classifier: Programming Language :: Python :: 3
License-File: LICENSE
Requires-Dist: selenium
Requires-Dist: webdriver-manager
Requires-Dist: PyExecJs
Requires-Dist: aiohttp
Requires-Dist: pytz
